tests/test_searchable.py
tests/test_refs.py
tests/__init__.py
tests/test_rawquery.py
tests/test_tags.py
tests/apps.py
tests/models.py
tests/urls.py
tests/test_templates.py
tests/test_handlers.py
tests/parsers/__init__.py
tests/parsers/test_query.py
tests/parsers/test_json.py
tests/serializers/__init__.py
tests/serializers/test_sql.py
tests/serializers/test_django.py
django_find/__init__.py
django_find/models.py
django_find/refs.py
django_find/tree.py
django_find/dom.py
django_find/version.py
django_find/rawquery.py
django_find/urls.py
django_find/model_helpers.py
django_find/apps.py
django_find/handlers.py
django_find/parsers/__init__.py
django_find/parsers/query.py
django_find/parsers/json.py
django_find/parsers/parser.py
django_find/serializers/__init__.py
django_find/serializers/serializer.py
django_find/serializers/django.py
django_find/serializers/sql.py
django_find/serializers/util.py
django_find/templatetags/find_tags.py
django_find/templatetags/__init__.py
django_find/templates/django_find/form.html
django_find/templates/django_find/headers.html
django_find/templates/django_find/result_table.html
django_find/templates/django_find/search.html
django_find-0.9.2.dist-info/top_level.txt
django_find-0.9.2.dist-info/METADATA
django_find-0.9.2.dist-info/DESCRIPTION.rst
django_find-0.9.2.dist-info/metadata.json
django_find-0.9.2.dist-info/WHEEL
django_find-0.9.2.dist-info/RECORD
