Metadata-Version: 2.0
Name: django-find
Version: 0.9.2
Summary: Simple but powerful search/filter functionality to Django projects
Home-page: https://github.com/knipknap/django-find
Author: Samuel Abels
Author-email: knipknap@gmail.com
License: MIT License
Keywords: django search find filter query json sql app
Platform: UNKNOWN
Classifier: Environment :: Web Environment
Classifier: Development Status :: 5 - Production/Stable
Classifier: Framework :: Django
Classifier: Framework :: Django :: 1.9
Classifier: Framework :: Django :: 1.10
Classifier: Framework :: Django :: 1.11
Classifier: Intended Audience :: Developers
Classifier: License :: OSI Approved :: MIT License
Classifier: Operating System :: OS Independent
Classifier: Programming Language :: Python
Classifier: Programming Language :: Python :: 2.7
Classifier: Programming Language :: Python :: 3.4
Classifier: Programming Language :: Python :: 3.5
Classifier: Programming Language :: Python :: 3.6
Classifier: Topic :: Internet :: WWW/HTTP
Classifier: Topic :: Internet :: WWW/HTTP :: Dynamic Content
Classifier: Topic :: Text Processing :: Filters
Requires-Dist: future
Requires-Dist: Django (>=1.11,<2)
Requires-Dist: mysqlclient
Requires-Dist: dateparser
